{"version":"0.4","title":"[Daven Demo] Our Services Morden","type":"page","content":[{"id":"419faeb5","elType":"section","settings":{"stretch_section":"section-stretched","lastudio_parallax_layout_list":[{"lastudio_parallax_layout_image":{"url":"https://draven.la-studioweb.com/wp-content/uploads/2018/12/services-morden-bg1.jpg","id":1598},"_id":"0d62ab8","lastudio_parallax_layout_speed":{"unit":"%","size":30},"lastudio_parallax_layout_type":"scroll","lastudio_parallax_layout_z_index":"","lastudio_parallax_layout_bg_x":50,"lastudio_parallax_layout_bg_y":50,"lastudio_parallax_layout_bg_size":"cover","lastudio_parallax_layout_animation_prop":"bgposition","lastudio_parallax_layout_on":["desktop","tablet"],"lastudio_parallax_layout_css_class":""}],"background_background":"classic","background_position":"center center","background_attachment":"fixed","background_repeat":"no-repeat","background_size":"cover","shape_divider_bottom_color":"rgba(245,62,106,0.8)","shape_divider_bottom_height":{"unit":"px","size":420}},"elements":[{"id":"6a0995d8","elType":"column","settings":{"_column_size":100,"_inline_maxwidth_laptop":800,"_inline_maxwidth_width800":600,"padding_tablet":{"unit":"px","top":"10","right":"10","bottom":"10","left":"40","isLinked":false}},"elements":[{"id":"255b3e7d","elType":"widget","settings":{"space":{"unit":"px","size":380},"space_laptop":{"unit":"px","size":240}},"elements":[],"widgetType":"spacer"},{"id":"212c1304","elType":"widget","settings":{"title":"Great Service, Professional Support","header_size":"h1","align":"left","title_color":"#ffffff","typography_typography":"custom","typography_font_size":{"unit":"px","size":80},"typography_font_weight":"bold","typography_text_transform":"uppercase","typography_letter_spacing":{"unit":"px","size":2},"typography_font_size_laptop":{"unit":"px","size":54},"typography_font_size_width800":{"unit":"px","size":40},"typography_font_size_width640":{"unit":"px","size":26}},"elements":[],"widgetType":"heading"},{"id":"6f231b8f","elType":"widget","settings":{"space":{"unit":"px","size":35},"space_laptop":{"unit":"px","size":20}},"elements":[],"widgetType":"spacer"},{"id":"16039493","elType":"widget","settings":{"title":"Home / About Us 02","header_size":"div","align":"left","title_color":"#ffffff","typography_typography":"custom","typography_font_size":{"unit":"px","size":20},"typography_font_size_width800":{"unit":"px","size":16}},"elements":[],"widgetType":"heading"},{"id":"7920fe47","elType":"widget","settings":{"space":{"unit":"px","size":260},"space_tablet":{"unit":"px","size":100},"space_laptop":{"unit":"px","size":200}},"elements":[],"widgetType":"spacer"}],"isInner":false}],"isInner":false},{"id":"b74727f","elType":"section","settings":{"lastudio_parallax_layout_list":[{"lastudio_parallax_layout_image":{"url":""},"_id":"7e58bb0","lastudio_parallax_layout_speed":{"unit":"%","size":50},"lastudio_parallax_layout_type":"scroll","lastudio_parallax_layout_z_index":"","lastudio_parallax_layout_bg_x":50,"lastudio_parallax_layout_bg_y":50,"lastudio_parallax_layout_bg_size":"auto","lastudio_parallax_layout_animation_prop":"transform","lastudio_parallax_layout_on":["desktop","tablet"],"lastudio_parallax_layout_css_class":""}]},"elements":[{"id":"4a1a26a","elType":"column","settings":{"_column_size":100,"_inline_maxwidth":750,"lastudio_column_align":"center"},"elements":[{"id":"d2fa16c","elType":"widget","settings":{"space":{"unit":"px","size":70}},"elements":[],"widgetType":"spacer"},{"id":"2158d1d","elType":"widget","settings":{"title":"OUR PROCESS","align":"center","typography_typography":"custom","typography_letter_spacing":{"unit":"px","size":2},"typography_font_weight":"bold"},"elements":[],"widgetType":"heading"},{"id":"df5e926","elType":"widget","settings":{"space":{"unit":"px","size":10}},"elements":[],"widgetType":"spacer"},{"id":"86a225b","elType":"widget","settings":{"title":"Mauris a ante quis enim rhoncus mattis quis et nunc. Maecenas auctor tellus sit amet. Fusce a augue lorem. Morbi ut orci nec","header_size":"p","align":"center","typography_typography":"custom","typography_font_size":{"unit":"px","size":18},"typography_line_height":{"unit":"em","size":2}},"elements":[],"widgetType":"heading"},{"id":"5db88ca","elType":"widget","settings":{"space_tablet":{"unit":"px","size":30}},"elements":[],"widgetType":"spacer"}],"isInner":false}],"isInner":false},{"id":"74799386","elType":"section","settings":{"stretch_section":"section-stretched","content_width":{"unit":"px","size":1760},"gap":"no","structure":"40","lastudio_parallax_layout_list":[{"lastudio_parallax_layout_image":{"url":""},"_id":"4e89aa2","lastudio_parallax_layout_speed":{"unit":"%","size":50},"lastudio_parallax_layout_type":"scroll","lastudio_parallax_layout_z_index":"","lastudio_parallax_layout_bg_x":50,"lastudio_parallax_layout_bg_y":50,"lastudio_parallax_layout_bg_size":"auto","lastudio_parallax_layout_animation_prop":"transform","lastudio_parallax_layout_on":["desktop","tablet"],"lastudio_parallax_layout_css_class":""}]},"elements":[{"id":"a39c4fe","elType":"column","settings":{"_column_size":25,"_inline_size":null,"_inline_maxwidth":350,"lastudio_column_align":"center","_inline_size_width800":50,"_inline_size_width640":100,"padding_laptop":{"unit":"px","top":"10","right":"10","bottom":"10","left":"10","isLinked":true}},"elements":[{"id":"47218c9c","elType":"widget","settings":{"icon":"dlicon business_bulb-62","view":"stacked","title_text":"01.Brainstorming","description_text":"Fusce a augue lorem. Morbi ut orci nec odio placerat viverra","link":{"url":"#","is_external":"","nofollow":""},"primary_color":"#f53e6a","icon_space":{"unit":"px","size":30},"icon_size":{"unit":"px","size":24},"icon_padding":{"unit":"px","size":28},"title_typography_typography":"custom","title_typography_font_size":{"unit":"px","size":18},"title_typography_text_transform":"uppercase","description_typography_typography":"custom","icon_space_tablet":{"unit":"px","size":10},"title_bottom_space_tablet":{"unit":"px","size":10},"title_bottom_space":{"unit":"px","size":10}},"elements":[],"widgetType":"icon-box"}],"isInner":false},{"id":"32e97957","elType":"column","settings":{"_column_size":25,"_inline_size":null,"_inline_maxwidth":350,"lastudio_column_align":"center","_inline_size_width800":50,"_inline_size_width640":100,"padding_laptop":{"unit":"px","top":"10","right":"10","bottom":"10","left":"10","isLinked":true}},"elements":[{"id":"1fc1b8e6","elType":"widget","settings":{"icon":"dlicon design-2_layout-25","view":"stacked","title_text":"02.Wireframe Design","description_text":"Fusce a augue lorem. Morbi ut orci nec odio placerat viverra","link":{"url":"#","is_external":"","nofollow":""},"primary_color":"#f53e6a","icon_space":{"unit":"px","size":30},"icon_size":{"unit":"px","size":24},"icon_padding":{"unit":"px","size":28},"title_typography_typography":"custom","title_typography_font_size":{"unit":"px","size":18},"title_typography_text_transform":"uppercase","description_typography_typography":"custom","icon_space_tablet":{"unit":"px","size":10},"title_bottom_space_tablet":{"unit":"px","size":10},"title_bottom_space":{"unit":"px","size":10}},"elements":[],"widgetType":"icon-box"}],"isInner":false},{"id":"208c9f13","elType":"column","settings":{"_column_size":25,"_inline_size":null,"_inline_maxwidth":350,"lastudio_column_align":"center","_inline_size_width800":50,"_inline_size_width640":100,"padding_laptop":{"unit":"px","top":"10","right":"10","bottom":"10","left":"10","isLinked":true}},"elements":[{"id":"4924d979","elType":"widget","settings":{"icon":"dlicon design-2_mirror","view":"stacked","title_text":"03.Development","description_text":"Fusce a augue lorem. Morbi ut orci nec odio placerat viverra","link":{"url":"#","is_external":"","nofollow":""},"primary_color":"#f53e6a","icon_space":{"unit":"px","size":30},"icon_size":{"unit":"px","size":24},"icon_padding":{"unit":"px","size":28},"title_typography_typography":"custom","title_typography_font_size":{"unit":"px","size":18},"title_typography_text_transform":"uppercase","description_typography_typography":"custom","icon_space_tablet":{"unit":"px","size":10},"title_bottom_space_tablet":{"unit":"px","size":10},"title_bottom_space":{"unit":"px","size":10}},"elements":[],"widgetType":"icon-box"}],"isInner":false},{"id":"d613f31","elType":"column","settings":{"_column_size":25,"_inline_size":null,"_inline_maxwidth":350,"lastudio_column_align":"center","_inline_size_width800":50,"_inline_size_width640":100,"padding_laptop":{"unit":"px","top":"10","right":"10","bottom":"10","left":"10","isLinked":true}},"elements":[{"id":"1db3c493","elType":"widget","settings":{"icon":"dlicon arrows-2_reload","view":"stacked","title_text":"04.Testing & Released","description_text":"Fusce a augue lorem. Morbi ut orci nec odio placerat viverra","link":{"url":"#","is_external":"","nofollow":""},"primary_color":"#f53e6a","icon_space":{"unit":"px","size":30},"icon_size":{"unit":"px","size":24},"icon_padding":{"unit":"px","size":28},"title_typography_typography":"custom","title_typography_font_size":{"unit":"px","size":18},"title_typography_text_transform":"uppercase","description_typography_typography":"custom","icon_space_tablet":{"unit":"px","size":10},"title_bottom_space_tablet":{"unit":"px","size":10},"title_bottom_space":{"unit":"px","size":10}},"elements":[],"widgetType":"icon-box"}],"isInner":false}],"isInner":false},{"id":"25142f5","elType":"section","settings":{"lastudio_parallax_layout_list":[{"lastudio_parallax_layout_image":{"url":""},"_id":"1fafccc","lastudio_parallax_layout_speed":{"unit":"%","size":50},"lastudio_parallax_layout_type":"scroll","lastudio_parallax_layout_z_index":"","lastudio_parallax_layout_bg_x":50,"lastudio_parallax_layout_bg_y":50,"lastudio_parallax_layout_bg_size":"auto","lastudio_parallax_layout_animation_prop":"transform","lastudio_parallax_layout_on":["desktop","tablet"],"lastudio_parallax_layout_css_class":""}]},"elements":[{"id":"706b969","elType":"column","settings":{"_column_size":100},"elements":[{"id":"fd500d2","elType":"widget","settings":{"space":{"unit":"px","size":80},"space_tablet":{"unit":"px","size":50}},"elements":[],"widgetType":"spacer"}],"isInner":false}],"isInner":false},{"id":"cfddc99","elType":"section","settings":{"stretch_section":"section-stretched","layout":"full_width","lastudio_parallax_layout_list":[{"lastudio_parallax_layout_image":{"url":""},"_id":"35960c0","lastudio_parallax_layout_speed":{"unit":"%","size":50},"lastudio_parallax_layout_type":"scroll","lastudio_parallax_layout_z_index":"","lastudio_parallax_layout_bg_x":50,"lastudio_parallax_layout_bg_y":50,"lastudio_parallax_layout_bg_size":"auto","lastudio_parallax_layout_animation_prop":"transform","lastudio_parallax_layout_on":["desktop","tablet"],"lastudio_parallax_layout_css_class":""}],"background_background":"classic","background_color":"#f9f9f9"},"elements":[{"id":"fc34c9f","elType":"column","settings":{"_column_size":100},"elements":[{"id":"93bd12d","elType":"section","settings":{"lastudio_parallax_layout_list":[{"lastudio_parallax_layout_image":{"url":""},"_id":"52efabe","lastudio_parallax_layout_speed":{"unit":"%","size":50},"lastudio_parallax_layout_type":"scroll","lastudio_parallax_layout_z_index":"","lastudio_parallax_layout_bg_x":50,"lastudio_parallax_layout_bg_y":50,"lastudio_parallax_layout_bg_size":"auto","lastudio_parallax_layout_animation_prop":"transform","lastudio_parallax_layout_on":["desktop","tablet"],"lastudio_parallax_layout_css_class":""}]},"elements":[{"id":"2697ac1","elType":"column","settings":{"_column_size":100,"_inline_size":null,"_inline_maxwidth":750,"lastudio_column_align":"center"},"elements":[{"id":"cfe822b","elType":"widget","settings":{"space":{"unit":"px","size":45},"space_tablet":{"unit":"px","size":30}},"elements":[],"widgetType":"spacer"},{"id":"564ae8e","elType":"widget","settings":{"title":"Core Services","align":"center","typography_typography":"custom","typography_text_transform":"uppercase","typography_letter_spacing":{"unit":"px","size":2},"typography_font_weight":"bold"},"elements":[],"widgetType":"heading"},{"id":"18e8255","elType":"widget","settings":{"space":{"unit":"px","size":10}},"elements":[],"widgetType":"spacer"},{"id":"74d5337","elType":"widget","settings":{"title":"Mauris a ante quis enim rhoncus mattis quis et nunc. Maecenas auctor tellus sit amet. Fusce a augue lorem. Morbi ut orci nec","header_size":"p","align":"center","typography_typography":"custom","typography_font_size":{"unit":"px","size":18},"typography_line_height":{"unit":"em","size":2}},"elements":[],"widgetType":"heading"},{"id":"0d95b1b","elType":"widget","settings":{"space":{"unit":"px","size":70},"space_tablet":{"unit":"px","size":20},"space_laptop":{"unit":"px","size":50}},"elements":[],"widgetType":"spacer"}],"isInner":true}],"isInner":true},{"id":"f6faf82","elType":"section","settings":{"gap":"no","structure":"30","lastudio_parallax_layout_list":[{"lastudio_parallax_layout_image":{"url":""},"_id":"a2479b7","lastudio_parallax_layout_speed":{"unit":"%","size":50},"lastudio_parallax_layout_type":"scroll","lastudio_parallax_layout_z_index":"","lastudio_parallax_layout_bg_x":50,"lastudio_parallax_layout_bg_y":50,"lastudio_parallax_layout_bg_size":"auto","lastudio_parallax_layout_animation_prop":"transform","lastudio_parallax_layout_on":["desktop","tablet"],"lastudio_parallax_layout_css_class":""}],"padding":{"unit":"px","top":"0","right":"40","bottom":"0","left":"40","isLinked":false},"content_width":{"unit":"px","size":1760},"padding_tablet":{"unit":"px","top":"20","right":"20","bottom":"20","left":"20","isLinked":true},"padding_width640":{"unit":"px","top":"0","right":"0","bottom":"0","left":"0","isLinked":true}},"elements":[{"id":"f814275","elType":"column","settings":{"_column_size":33,"_inline_size":null,"_inline_size_width800":100,"padding":{"unit":"px","top":"35","right":"35","bottom":"35","left":"35","isLinked":true},"padding_tablet":{"unit":"px","top":"10","right":"10","bottom":"10","left":"10","isLinked":true},"padding_laptop":{"unit":"px","top":"20","right":"20","bottom":"20","left":"20","isLinked":true}},"elements":[{"id":"3492d94a","elType":"widget","settings":{"services_icon":"dlicon design_wand-11","services_title":"Design Services","services_description":"Mauris a ante quis enim rhoncus mattis quis et nunc. Maecenas auctor tellus sit amet..Fusce a augue lorem. Morbi ut orci nec odio placerat viverra","button_text":"READ MORE","button_url":{"url":"#","is_external":"","nofollow":""},"container_background_background":"classic","container_background_color":"#ffffff","header_width":{"unit":"px","size":250},"header_height":{"unit":"px","size":250},"icon_color":"#f53e6a","icon_bg_color":"#ffffff","icon_font_size":{"unit":"px","size":40},"icon_size":{"unit":"px","size":150},"icon_box_shadow_box_shadow_type":"yes","icon_box_shadow_box_shadow":{"horizontal":0,"vertical":0,"blur":55,"spread":0,"color":"#dadada"},"use_title_icon":"","title_typography_typography":"custom","title_typography_font_size":{"unit":"px","size":24},"title_typography_font_weight":"bold","title_margin":{"unit":"px","top":"-10","right":"0","bottom":"10","left":"0","isLinked":false},"desc_color":"#535353","desc_typography_typography":"custom","desc_typography_font_weight":"normal","desc_typography_line_height":{"unit":"em","size":2},"desc_padding":{"unit":"px","top":"0","right":"30","bottom":"0","left":"30","isLinked":false},"desc_margin":{"unit":"px","top":"0","right":"0","bottom":"80","left":"0","isLinked":false},"button_cover_location":"","add_button_icon":"","button_bg_color":"#f53e6a","button_color":"#ffffff","button_typography_typography":"custom","button_typography_font_size":{"unit":"px","size":14},"button_typography_font_weight":"bold","button_typography_line_height":{"unit":"px","size":20},"button_padding":{"unit":"px","top":"35","right":"35","bottom":"35","left":"35","isLinked":true},"button_border_radius":{"unit":"px","top":"0","right":"0","bottom":"0","left":"0","isLinked":true},"button_fullwidth":"yes","primary_button_hover_bg_color":"#000000","button_hover_color":"#ffffff","show_on_hover":"","header_height_tablet":{"unit":"px","size":180},"icon_font_size_tablet":{"unit":"px","size":30},"icon_size_tablet":{"unit":"px","size":100},"title_typography_font_size_tablet":{"unit":"px","size":18},"desc_typography_font_size_tablet":{"unit":"px","size":16},"desc_padding_tablet":{"unit":"px","top":"0","right":"20","bottom":"0","left":"20","isLinked":false},"desc_margin_tablet":{"unit":"px","top":"0","right":"0","bottom":"30","left":"0","isLinked":false},"button_padding_tablet":{"unit":"px","top":"25","right":"25","bottom":"25","left":"25","isLinked":true}},"elements":[],"widgetType":"lastudio-services"}],"isInner":true},{"id":"77ad921","elType":"column","settings":{"_column_size":33,"_inline_size":null,"_inline_size_width800":100,"padding":{"unit":"px","top":"35","right":"35","bottom":"35","left":"35","isLinked":true},"padding_tablet":{"unit":"px","top":"10","right":"10","bottom":"10","left":"10","isLinked":true},"padding_laptop":{"unit":"px","top":"20","right":"20","bottom":"20","left":"20","isLinked":true}},"elements":[{"id":"16dbc4f5","elType":"widget","settings":{"services_icon":"dlicon business_chart-bar-33","services_title":"Marketing Automation","services_description":"Mauris a ante quis enim rhoncus mattis quis et nunc. Maecenas auctor tellus sit amet..Fusce a augue lorem. Morbi ut orci nec odio placerat viverra","button_text":"READ MORE","button_url":{"url":"#","is_external":"","nofollow":""},"container_background_background":"classic","container_background_color":"#ffffff","header_width":{"unit":"px","size":250},"header_height":{"unit":"px","size":250},"icon_color":"#f53e6a","icon_bg_color":"#ffffff","icon_font_size":{"unit":"px","size":40},"icon_size":{"unit":"px","size":150},"icon_box_shadow_box_shadow_type":"yes","icon_box_shadow_box_shadow":{"horizontal":0,"vertical":0,"blur":55,"spread":0,"color":"#dadada"},"use_title_icon":"","title_typography_typography":"custom","title_typography_font_size":{"unit":"px","size":24},"title_typography_font_weight":"bold","title_margin":{"unit":"px","top":"-10","right":"0","bottom":"10","left":"0","isLinked":false},"desc_color":"#535353","desc_typography_typography":"custom","desc_typography_font_weight":"normal","desc_typography_line_height":{"unit":"em","size":2},"desc_padding":{"unit":"px","top":"0","right":"30","bottom":"0","left":"30","isLinked":false},"desc_margin":{"unit":"px","top":"0","right":"0","bottom":"80","left":"0","isLinked":false},"button_cover_location":"","add_button_icon":"","button_bg_color":"#f53e6a","button_color":"#ffffff","button_typography_typography":"custom","button_typography_font_size":{"unit":"px","size":14},"button_typography_font_weight":"bold","button_typography_line_height":{"unit":"px","size":20},"button_padding":{"unit":"px","top":"35","right":"35","bottom":"35","left":"35","isLinked":true},"button_border_radius":{"unit":"px","top":"0","right":"0","bottom":"0","left":"0","isLinked":true},"button_fullwidth":"yes","primary_button_hover_bg_color":"#000000","button_hover_color":"#ffffff","header_height_tablet":{"unit":"px","size":180},"icon_font_size_tablet":{"unit":"px","size":30},"icon_size_tablet":{"unit":"px","size":100},"title_typography_font_size_tablet":{"unit":"px","size":18},"desc_typography_font_size_tablet":{"unit":"px","size":16},"desc_padding_tablet":{"unit":"px","top":"0","right":"20","bottom":"0","left":"20","isLinked":false},"desc_margin_tablet":{"unit":"px","top":"0","right":"0","bottom":"30","left":"0","isLinked":false},"button_padding_tablet":{"unit":"px","top":"25","right":"25","bottom":"25","left":"25","isLinked":true},"show_on_hover":""},"elements":[],"widgetType":"lastudio-services"}],"isInner":true},{"id":"822a15b","elType":"column","settings":{"_column_size":33,"_inline_size":null,"_inline_size_width800":100,"padding":{"unit":"px","top":"35","right":"35","bottom":"35","left":"35","isLinked":true},"padding_tablet":{"unit":"px","top":"10","right":"10","bottom":"10","left":"10","isLinked":true},"padding_laptop":{"unit":"px","top":"20","right":"20","bottom":"20","left":"20","isLinked":true}},"elements":[{"id":"6424924","elType":"widget","settings":{"services_icon":"dlicon design_window-code","services_title":"Web Development","services_description":"Mauris a ante quis enim rhoncus mattis quis et nunc. Maecenas auctor tellus sit amet..Fusce a augue lorem. Morbi ut orci nec odio placerat viverra","button_text":"READ MORE","button_url":{"url":"#","is_external":"","nofollow":""},"container_background_background":"classic","container_background_color":"#ffffff","header_width":{"unit":"px","size":250},"header_height":{"unit":"px","size":250},"icon_color":"#f53e6a","icon_bg_color":"#ffffff","icon_font_size":{"unit":"px","size":40},"icon_size":{"unit":"px","size":150},"icon_box_shadow_box_shadow_type":"yes","icon_box_shadow_box_shadow":{"horizontal":0,"vertical":0,"blur":55,"spread":0,"color":"#dadada"},"use_title_icon":"","title_typography_typography":"custom","title_typography_font_size":{"unit":"px","size":24},"title_typography_font_weight":"bold","title_margin":{"unit":"px","top":"-10","right":"0","bottom":"10","left":"0","isLinked":false},"desc_color":"#535353","desc_typography_typography":"custom","desc_typography_font_weight":"normal","desc_typography_line_height":{"unit":"em","size":2},"desc_padding":{"unit":"px","top":"0","right":"30","bottom":"0","left":"30","isLinked":false},"desc_margin":{"unit":"px","top":"0","right":"0","bottom":"80","left":"0","isLinked":false},"button_cover_location":"","add_button_icon":"","button_bg_color":"#f53e6a","button_color":"#ffffff","button_typography_typography":"custom","button_typography_font_size":{"unit":"px","size":14},"button_typography_font_weight":"bold","button_typography_line_height":{"unit":"px","size":20},"button_padding":{"unit":"px","top":"35","right":"35","bottom":"35","left":"35","isLinked":true},"button_border_radius":{"unit":"px","top":"0","right":"0","bottom":"0","left":"0","isLinked":true},"button_fullwidth":"yes","primary_button_hover_bg_color":"#000000","button_hover_color":"#ffffff","header_height_tablet":{"unit":"px","size":180},"icon_font_size_tablet":{"unit":"px","size":30},"icon_size_tablet":{"unit":"px","size":100},"title_typography_font_size_tablet":{"unit":"px","size":18},"desc_typography_font_size_tablet":{"unit":"px","size":16},"desc_padding_tablet":{"unit":"px","top":"0","right":"20","bottom":"0","left":"20","isLinked":false},"desc_margin_tablet":{"unit":"px","top":"0","right":"0","bottom":"30","left":"0","isLinked":false},"button_padding_tablet":{"unit":"px","top":"25","right":"25","bottom":"25","left":"25","isLinked":true},"show_on_hover":""},"elements":[],"widgetType":"lastudio-services"}],"isInner":true}],"isInner":true},{"id":"020e73c","elType":"section","settings":{"gap":"no","structure":"30","lastudio_parallax_layout_list":[{"lastudio_parallax_layout_image":{"url":""},"_id":"a2479b7","lastudio_parallax_layout_speed":{"unit":"%","size":50},"lastudio_parallax_layout_type":"scroll","lastudio_parallax_layout_z_index":"","lastudio_parallax_layout_bg_x":50,"lastudio_parallax_layout_bg_y":50,"lastudio_parallax_layout_bg_size":"auto","lastudio_parallax_layout_animation_prop":"transform","lastudio_parallax_layout_on":["desktop","tablet"],"lastudio_parallax_layout_css_class":""}],"padding":{"unit":"px","top":"0","right":"40","bottom":"0","left":"40","isLinked":false},"content_width":{"unit":"px","size":1760},"padding_tablet":{"unit":"px","top":"10","right":"10","bottom":"10","left":"10","isLinked":true},"padding_width640":{"unit":"px","top":"0","right":"0","bottom":"0","left":"0","isLinked":true}},"elements":[{"id":"cec3edf","elType":"column","settings":{"_column_size":33,"_inline_size":null,"_inline_size_width800":100,"padding":{"unit":"px","top":"35","right":"35","bottom":"35","left":"35","isLinked":true},"padding_tablet":{"unit":"px","top":"10","right":"10","bottom":"10","left":"10","isLinked":true},"padding_laptop":{"unit":"px","top":"20","right":"20","bottom":"20","left":"20","isLinked":true}},"elements":[{"id":"e2a7a05","elType":"widget","settings":{"services_icon":"dlicon tech_computer-monitor","services_title":"Motion Digital","services_description":"Mauris a ante quis enim rhoncus mattis quis et nunc. Maecenas auctor tellus sit amet..Fusce a augue lorem. Morbi ut orci nec odio placerat viverra","button_text":"READ MORE","button_url":{"url":"#","is_external":"","nofollow":""},"container_background_background":"classic","container_background_color":"#ffffff","header_width":{"unit":"px","size":250},"header_height":{"unit":"px","size":250},"icon_color":"#f53e6a","icon_bg_color":"#ffffff","icon_font_size":{"unit":"px","size":40},"icon_size":{"unit":"px","size":150},"icon_box_shadow_box_shadow_type":"yes","icon_box_shadow_box_shadow":{"horizontal":0,"vertical":0,"blur":55,"spread":0,"color":"#dadada"},"use_title_icon":"","title_typography_typography":"custom","title_typography_font_size":{"unit":"px","size":24},"title_typography_font_weight":"bold","title_margin":{"unit":"px","top":"-10","right":"0","bottom":"10","left":"0","isLinked":false},"desc_color":"#535353","desc_typography_typography":"custom","desc_typography_font_weight":"normal","desc_typography_line_height":{"unit":"em","size":2},"desc_padding":{"unit":"px","top":"0","right":"30","bottom":"0","left":"30","isLinked":false},"desc_margin":{"unit":"px","top":"0","right":"0","bottom":"80","left":"0","isLinked":false},"button_cover_location":"","add_button_icon":"","button_bg_color":"#f53e6a","button_color":"#ffffff","button_typography_typography":"custom","button_typography_font_size":{"unit":"px","size":14},"button_typography_font_weight":"bold","button_typography_line_height":{"unit":"px","size":20},"button_padding":{"unit":"px","top":"35","right":"35","bottom":"35","left":"35","isLinked":true},"button_border_radius":{"unit":"px","top":"0","right":"0","bottom":"0","left":"0","isLinked":true},"button_fullwidth":"yes","primary_button_hover_bg_color":"#000000","button_hover_color":"#ffffff","show_on_hover":"","header_height_tablet":{"unit":"px","size":180},"icon_font_size_tablet":{"unit":"px","size":30},"icon_size_tablet":{"unit":"px","size":100},"title_typography_font_size_tablet":{"unit":"px","size":18},"desc_typography_font_size_tablet":{"unit":"px","size":16},"desc_padding_tablet":{"unit":"px","top":"0","right":"20","bottom":"0","left":"20","isLinked":false},"desc_margin_tablet":{"unit":"px","top":"0","right":"0","bottom":"30","left":"0","isLinked":false},"button_padding_tablet":{"unit":"px","top":"25","right":"25","bottom":"25","left":"25","isLinked":true}},"elements":[],"widgetType":"lastudio-services"}],"isInner":true},{"id":"fedc43a","elType":"column","settings":{"_column_size":33,"_inline_size":null,"_inline_size_width800":100,"padding":{"unit":"px","top":"35","right":"35","bottom":"35","left":"35","isLinked":true},"padding_tablet":{"unit":"px","top":"10","right":"10","bottom":"10","left":"10","isLinked":true},"padding_laptop":{"unit":"px","top":"20","right":"20","bottom":"20","left":"20","isLinked":true}},"elements":[{"id":"bc195b4","elType":"widget","settings":{"services_icon":"dlicon files_drawer","services_title":"Interior Design","services_description":"Mauris a ante quis enim rhoncus mattis quis et nunc. Maecenas auctor tellus sit amet..Fusce a augue lorem. Morbi ut orci nec odio placerat viverra","button_text":"READ MORE","button_url":{"url":"#","is_external":"","nofollow":""},"container_background_background":"classic","container_background_color":"#ffffff","header_width":{"unit":"px","size":250},"header_height":{"unit":"px","size":250},"icon_color":"#f53e6a","icon_bg_color":"#ffffff","icon_font_size":{"unit":"px","size":40},"icon_size":{"unit":"px","size":150},"icon_box_shadow_box_shadow_type":"yes","icon_box_shadow_box_shadow":{"horizontal":0,"vertical":0,"blur":55,"spread":0,"color":"#dadada"},"use_title_icon":"","title_typography_typography":"custom","title_typography_font_size":{"unit":"px","size":24},"title_typography_font_weight":"bold","title_margin":{"unit":"px","top":"-10","right":"0","bottom":"10","left":"0","isLinked":false},"desc_color":"#535353","desc_typography_typography":"custom","desc_typography_font_weight":"normal","desc_typography_line_height":{"unit":"em","size":2},"desc_padding":{"unit":"px","top":"0","right":"30","bottom":"0","left":"30","isLinked":false},"desc_margin":{"unit":"px","top":"0","right":"0","bottom":"80","left":"0","isLinked":false},"button_cover_location":"","add_button_icon":"","button_bg_color":"#f53e6a","button_color":"#ffffff","button_typography_typography":"custom","button_typography_font_size":{"unit":"px","size":14},"button_typography_font_weight":"bold","button_typography_line_height":{"unit":"px","size":20},"button_padding":{"unit":"px","top":"35","right":"35","bottom":"35","left":"35","isLinked":true},"button_border_radius":{"unit":"px","top":"0","right":"0","bottom":"0","left":"0","isLinked":true},"button_fullwidth":"yes","primary_button_hover_bg_color":"#000000","button_hover_color":"#ffffff","header_height_tablet":{"unit":"px","size":180},"icon_font_size_tablet":{"unit":"px","size":30},"icon_size_tablet":{"unit":"px","size":100},"title_typography_font_size_tablet":{"unit":"px","size":18},"desc_typography_font_size_tablet":{"unit":"px","size":16},"desc_padding_tablet":{"unit":"px","top":"0","right":"20","bottom":"0","left":"20","isLinked":false},"desc_margin_tablet":{"unit":"px","top":"0","right":"0","bottom":"30","left":"0","isLinked":false},"button_padding_tablet":{"unit":"px","top":"25","right":"25","bottom":"25","left":"25","isLinked":true},"show_on_hover":""},"elements":[],"widgetType":"lastudio-services"}],"isInner":true},{"id":"7951167","elType":"column","settings":{"_column_size":33,"_inline_size":null,"_inline_size_width800":100,"padding":{"unit":"px","top":"35","right":"35","bottom":"35","left":"35","isLinked":true},"padding_tablet":{"unit":"px","top":"10","right":"10","bottom":"10","left":"10","isLinked":true},"padding_laptop":{"unit":"px","top":"20","right":"20","bottom":"20","left":"20","isLinked":true}},"elements":[{"id":"6328374","elType":"widget","settings":{"services_icon":"fa fa-database","services_title":"Data Management","services_description":"Mauris a ante quis enim rhoncus mattis quis et nunc. Maecenas auctor tellus sit amet..Fusce a augue lorem. Morbi ut orci nec odio placerat viverra","button_text":"READ MORE","button_url":{"url":"#","is_external":"","nofollow":""},"container_background_background":"classic","container_background_color":"#ffffff","header_width":{"unit":"px","size":250},"header_height":{"unit":"px","size":250},"icon_color":"#f53e6a","icon_bg_color":"#ffffff","icon_font_size":{"unit":"px","size":40},"icon_size":{"unit":"px","size":150},"icon_box_shadow_box_shadow_type":"yes","icon_box_shadow_box_shadow":{"horizontal":0,"vertical":0,"blur":55,"spread":0,"color":"#dadada"},"use_title_icon":"","title_typography_typography":"custom","title_typography_font_size":{"unit":"px","size":24},"title_typography_font_weight":"bold","title_margin":{"unit":"px","top":"-10","right":"0","bottom":"10","left":"0","isLinked":false},"desc_color":"#535353","desc_typography_typography":"custom","desc_typography_font_weight":"normal","desc_typography_line_height":{"unit":"em","size":2},"desc_padding":{"unit":"px","top":"0","right":"30","bottom":"0","left":"30","isLinked":false},"desc_margin":{"unit":"px","top":"0","right":"0","bottom":"80","left":"0","isLinked":false},"button_cover_location":"","add_button_icon":"","button_bg_color":"#f53e6a","button_color":"#ffffff","button_typography_typography":"custom","button_typography_font_size":{"unit":"px","size":14},"button_typography_font_weight":"bold","button_typography_line_height":{"unit":"px","size":20},"button_padding":{"unit":"px","top":"35","right":"35","bottom":"35","left":"35","isLinked":true},"button_border_radius":{"unit":"px","top":"0","right":"0","bottom":"0","left":"0","isLinked":true},"button_fullwidth":"yes","primary_button_hover_bg_color":"#000000","button_hover_color":"#ffffff","header_height_tablet":{"unit":"px","size":180},"icon_font_size_tablet":{"unit":"px","size":30},"icon_size_tablet":{"unit":"px","size":100},"title_typography_font_size_tablet":{"unit":"px","size":18},"desc_typography_font_size_tablet":{"unit":"px","size":16},"desc_padding_tablet":{"unit":"px","top":"0","right":"20","bottom":"0","left":"20","isLinked":false},"desc_margin_tablet":{"unit":"px","top":"0","right":"0","bottom":"30","left":"0","isLinked":false},"button_padding_tablet":{"unit":"px","top":"25","right":"25","bottom":"25","left":"25","isLinked":true},"show_on_hover":""},"elements":[],"widgetType":"lastudio-services"}],"isInner":true}],"isInner":true},{"id":"33461b5","elType":"widget","settings":{"space":{"unit":"px","size":160},"space_tablet":{"unit":"px","size":50},"space_laptop":{"unit":"px","size":80}},"elements":[],"widgetType":"spacer"}],"isInner":false}],"isInner":false},{"id":"50f50786","elType":"section","settings":{"stretch_section":"section-stretched","lastudio_parallax_layout_list":[{"lastudio_parallax_layout_image":{"url":"https://draven.la-studioweb.com/wp-content/uploads/2018/12/about-us2-bg3.jpg","id":1100},"_id":"0a97181","lastudio_parallax_layout_speed":{"unit":"%","size":20},"lastudio_parallax_layout_type":"scroll","lastudio_parallax_layout_z_index":"","lastudio_parallax_layout_bg_x":50,"lastudio_parallax_layout_bg_y":50,"lastudio_parallax_layout_bg_size":"cover","lastudio_parallax_layout_animation_prop":"bgposition","lastudio_parallax_layout_on":["desktop","tablet"],"lastudio_parallax_layout_css_class":""}]},"elements":[{"id":"13f2f9fb","elType":"column","settings":{"_column_size":100,"_inline_maxwidth_laptop":800,"_inline_maxwidth_width800":700,"lastudio_column_align_laptop":"center","lastudio_column_align_width800":"center"},"elements":[{"id":"18c6cf36","elType":"widget","settings":{"space":{"unit":"px","size":90},"space_width800":{"unit":"px","size":50}},"elements":[],"widgetType":"spacer"},{"id":"4590b0eb","elType":"widget","settings":{"image":{"url":"https://draven.la-studioweb.com/wp-content/uploads/2018/12/quote.png","id":1101},"image_size":"full","align":"center"},"elements":[],"widgetType":"image"},{"id":"5c8db6a","elType":"widget","settings":{"space":{"unit":"px","size":20}},"elements":[],"widgetType":"spacer"},{"id":"14f2d378","elType":"widget","settings":{"preset":"type-3","enable_carousel":"true","autoplay":"","adaptive_height":"","item_list":[{"item_comment":"Customer Support has been awesome! I'm somewhat of a beginner when it comes to Word Press, and they've helped me set up and answer questions. Very responsive, and I'm very grateful for their Customer Support Team! 5 Stars all the way!","item_name":"Olivia Arribas","item_position":"Louisville","item_rating":10,"_id":"025ec3a","item_image":{"url":"","id":""},"item_icon":"","item_title":""},{"item_comment":"Customer Support has been awesome! I'm somewhat of a beginner when it comes to Word Press, and they've helped me set up and answer questions. Very responsive, and I'm very grateful for their Customer Support Team! 5 Stars all the way!","item_name":"Essie Perkins","item_position":"CEO Apple","item_rating":10,"_id":"9f78df7","item_image":{"url":"","id":""},"item_icon":"","item_title":""}],"dots_style_popover_toggle":"custom","dots_style_background":"color","dots_style_color":"rgba(255,255,255,0.3)","dots_style_hover_popover_toggle":"custom","dots_style_hover_color":"#ffffff","dots_style_active_popover_toggle":"custom","dots_style_active_background":"color","dots_style_active_color":"#ffffff","comment_color":"#ffffff","comment_typography_typography":"custom","comment_typography_font_family":"Playfair Display","comment_typography_font_weight":"bold","comment_typography_line_height":{"unit":"em","size":1.6000000000000001},"comment_margin":{"unit":"px","top":"0","right":"0","bottom":"40","left":"0","isLinked":false},"name_color":"#ffffff","position_color":"#ffffff","comment_typography_font_size":{"unit":"px","size":36},"comment_typography_font_size_laptop":{"unit":"px","size":26},"comment_typography_font_size_width800":{"unit":"px","size":20},"name_typography_typography":"custom","name_typography_font_size_laptop":{"unit":"px","size":18}},"elements":[],"widgetType":"lastudio-testimonials"},{"id":"3e98bc90","elType":"widget","settings":{"space":{"unit":"px","size":100},"space_width800":{"unit":"px","size":50}},"elements":[],"widgetType":"spacer"}],"isInner":false}],"isInner":false},{"id":"7a6ae563","elType":"section","settings":{"stretch_section":"section-stretched","structure":"20","lastudio_parallax_layout_list":[{"lastudio_parallax_layout_image":{"url":""},"_id":"1f6cd35","lastudio_parallax_layout_speed":{"unit":"%","size":50},"lastudio_parallax_layout_type":"scroll","lastudio_parallax_layout_z_index":"","lastudio_parallax_layout_bg_x":50,"lastudio_parallax_layout_bg_y":50,"lastudio_parallax_layout_bg_size":"auto","lastudio_parallax_layout_animation_prop":"transform","lastudio_parallax_layout_on":["desktop","tablet"],"lastudio_parallax_layout_css_class":""}],"gap":"wider","fix_columns_alignment":"enabled","content_width":{"unit":"px","size":1600},"background_background":"classic","background_position":"bottom center","background_repeat":"no-repeat"},"elements":[{"id":"1c6bd1f0","elType":"column","settings":{"_column_size":50,"_inline_size":null,"_inline_maxwidth":530,"background_background":"classic","background_position":"bottom center","background_repeat":"no-repeat","_inline_size_tablet":30,"_inline_size_laptop":45,"_inline_size_width800":100,"lastudio_column_align":"left","padding_laptop":{"unit":"px","top":"30","right":"30","bottom":"30","left":"50","isLinked":false},"padding_width800":{"unit":"px","top":"20","right":"20","bottom":"20","left":"20","isLinked":true}},"elements":[{"id":"24b1ba10","elType":"widget","settings":{"space":{"unit":"px","size":180},"space_tablet":{"unit":"px","size":50},"space_laptop":{"unit":"px","size":180}},"elements":[],"widgetType":"spacer"},{"id":"1c8c318a","elType":"widget","settings":{"title":"LET'S TALK","typography_typography":"custom","typography_text_transform":"uppercase","typography_letter_spacing":{"unit":"px","size":2},"typography_font_weight":"bold"},"elements":[],"widgetType":"heading"},{"id":"dacafa6","elType":"widget","settings":{"space":{"unit":"px","size":20}},"elements":[],"widgetType":"spacer"},{"id":"631ba27","elType":"widget","settings":{"title":"Ut in massa in quam cursus dapibus at quis tortor. Curabitur volutpat vitae ligula eu viverra.","header_size":"p","typography_typography":"custom","typography_font_size":{"unit":"px","size":18},"typography_line_height":{"unit":"em","size":2},"typography_font_size_width640":{"unit":"px","size":16},"typography_font_size_tablet":{"unit":"px","size":16}},"elements":[],"widgetType":"heading"},{"id":"1ce679ba","elType":"widget","settings":{"space":{"unit":"px","size":40},"space_width800":{"unit":"px","size":0}},"elements":[],"widgetType":"spacer"}],"isInner":false},{"id":"57043896","elType":"column","settings":{"_column_size":50,"_inline_size":null,"_inline_maxwidth":800,"lastudio_column_align":"right","_inline_size_tablet":70,"_inline_size_laptop":55,"_inline_size_width800":100},"elements":[{"id":"bf805f2","elType":"widget","settings":{"space_tablet":{"unit":"px","size":30},"space_width800":{"unit":"px","size":0}},"elements":[],"widgetType":"spacer"},{"id":"12cfcbda","elType":"widget","settings":{"form_shortcode":"784::Home 10 Contact Form","text_typography_typography":"custom","input_typography_typography":"custom","input_typography_font_size":{"unit":"px","size":18},"input_padding":{"unit":"px","top":"15","right":"0","bottom":"15","left":"0","isLinked":false},"input_margin":{"unit":"px","top":"0","right":"0","bottom":"30","left":"0","isLinked":false},"input_border_border":"solid","input_border_width":{"unit":"px","top":"0","right":"0","bottom":"1","left":"0","isLinked":false},"textarea_min_height":200,"invalid_notice_margin":{"unit":"px","top":"0","right":"0","bottom":"0","left":"0","isLinked":true},"submit_bg_color":"#f53e6a","submit_typography_typography":"custom","submit_typography_font_size":{"unit":"px","size":18},"submit_typography_font_weight":"bold","submit_typography_line_height":{"unit":"px","size":""},"submit_padding":{"unit":"px","top":"30","right":"30","bottom":"30","left":"30","isLinked":true},"submit_border_radius":{"unit":"px","top":"0","right":"0","bottom":"0","left":"0","isLinked":true},"submit_hover_bg_color":"#2f2f2f","arrows":"block","submit_margin":{"unit":"px","top":"0","right":"0","bottom":"0","left":"0","isLinked":true},"input_background_color":"#ffffff","submit_typography_text_transform":"capitalize","input_typography_font_size_width640":{"unit":"px","size":16},"input_margin_tablet":{"unit":"px","top":"0","right":"0","bottom":"10","left":"0","isLinked":false},"submit_typography_font_size_tablet":{"unit":"px","size":18},"submit_padding_tablet":{"unit":"px","top":"20","right":"20","bottom":"20","left":"20","isLinked":true},"input_border_color":"#2f2f2f"},"elements":[],"widgetType":"contact-form-7"},{"id":"49be4ef3","elType":"widget","settings":{"space_tablet":{"unit":"px","size":30}},"elements":[],"widgetType":"spacer"}],"isInner":false}],"isInner":false}]}